<?xml version="1.0" encoding="UTF-8"?>
<monster name="Infernus" nameDescription="a Infernus" race="undead" experience="0" speed="370" manacost="0">
	<health now="112000" max="112000"/>
	<look type="201" corpse="5995"/>
	<targetchange interval="5000" chance="8"/>
	<strategy attack="100" defense="0"/>
	<flags>
		<flag summonable="0"/>
		<flag attackable="1"/>
		<flag hostile="1"/>
		<flag illusionable="0"/>
		<flag convinceable="0"/>
		<flag pushable="0"/>
		<flag canpushitems="1"/>
		<flag canpushcreatures="1"/>
		<flag targetdistance="1"/>
		<flag staticattack="90"/>
		<flag runonhealth="2500"/>
	</flags>
	<attacks>
		<attack name="melee" interval="2000" skill="250" attack="250"/>
		<attack name="manadrain" interval="1000" chance="7" range="7" min="-300" max="-600"/>
		<attack name="manadrain" interval="1000" chance="6" radius="5" target="0" min="-150" max="-350">
			<attribute key="areaEffect" value="HOLYDAMAGE"/>
		</attack>
		<attack name="fire" interval="1500" chance="6" radius="5" target="0">
			<attribute key="areaEffect" value="GROUNDSHAKER"/>
		</attack>
		<attack name="energy" interval="1000" chance="70" length="8" spread="0" min="-1820" max="-2380">
			<attribute key="areaEffect" value="PURPLEENERGY"/>
		</attack>
		<attack name="fire" interval="1000" chance="34" range="7" radius="5" target="1" min="-710" max="-950">
			<attribute key="shootEffect" value="holy"/>
			<attribute key="areaEffect" value="HOLYDAMAGE"/>
		</attack>
		<attack name="firefield" interval="1900" chance="10" range="7" radius="4" target="1">
			<attribute key="shootEffect" value="fire"/>
		</attack>
		<attack name="fire" interval="1000" chance="15" range="7" radius="5" min="-800" max="-1000">
			<attribute key="areaEffect" value="BIGCLOUDS"/>
		</attack>
	</attacks>
	<defenses armor="40" defense="45">
	</defenses>
	<immunities>
		<immunity lifedrain="1"/>
		<immunity paralyze="1"/>
		<immunity invisible="1"/>
	</immunities>
	<elements>
		<element physicalPercent="80"/>
		<element earthPercent="80"/>
		<element energyPercent="100"/>
		<element deathPercent="80"/>
		<element icePercent="80"/>
		<element holyPercent="80"/>
	</elements>
	<summons maxSummons="1">
		<summon name="firelord" interval="1000" chance="10" max="1"/>
	</summons>
	<voices interval="5000" chance="10">
		<voice sentence="PRAISED BE MY MASTERS, THE RUTHLESS SEVEN!" yell="1"/>
		<voice sentence="YOU ARE DOOMED!" yell="1"/>
		<voice sentence="INFERNUS IS BACK!" yell="1"/>
		<voice sentence="Be prepared for the day my masters will come for you!"/>
		<voice sentence="SOULS FOR INFERNUS!" yell="1"/>
	</voices>
</monster>