<raid>
<announce delay="0" message="The seals on Ferumbras old cidatel at the Forgotten City are glowing. Prepare for HIS return mortals." />
<announce delay="300000" message="Ferumbras return is at hand. The Great Kingdom Academy calls for Heroes to fight that evil." />
<announce delay="600000" message="Ferumbras has returned to his citadel once more. Stop him before its too late." />
<singlespawn delay="600000" name="Ferumbras" x="500" y="444" z="4" />
<singlespawn delay="600000" name="Demon" x="499" y="440" z="4" />
<singlespawn delay="600000" name="Demon" x="502" y="440" z="4" />
<singlespawn delay="600000" name="Demon" x="499" y="448" z="4" />
<singlespawn delay="600000" name="Demon" x="502" y="448" z="4" />
</raid>